{
  "hash": "21d51428",
  "configHash": "f09cf5c6",
  "lockfileHash": "d12bc831",
  "browserHash": "ffa8e1bc",
  "optimized": {
    "react": {
      "src": "../../node_modules/react/index.js",
      "file": "react.js",
      "fileHash": "af013c13",
      "needsInterop": true
    },
    "react-dom/client": {
      "src": "../../node_modules/react-dom/client.js",
      "file": "react-dom_client.js",
      "fileHash": "8a61e5a9",
      "needsInterop": true
    },
    "react-router-dom": {
      "src": "../../node_modules/react-router-dom/dist/index.js",
      "file": "react-router-dom.js",
      "fileHash": "a6c1225b",
      "needsInterop": false
    },
    "lucide-react": {
      "src": "../../node_modules/lucide-react/dist/esm/lucide-react.js",
      "file": "lucide-react.js",
      "fileHash": "702eb48f",
      "needsInterop": false
    }
  },
  "chunks": {
    "chunk-LV7LEDEA": {
      "file": "chunk-LV7LEDEA.js"
    },
    "chunk-JRE55LYH": {
      "file": "chunk-JRE55LYH.js"
    }
  }
}